{
  "HighRisk":{
    "cntGFC":0,
    "area_sqm":0.0,
    "hectare":0.0,
    "Thai_rai":0.0,
    "area_perc_":0.0,
    "area_perc":"0.0%"
  },
  "MediumRiskTH":{
    "cntGFC":0,
    "area_sqm":0.0,
    "hectare":0.0,
    "Thai_rai":0.0,
    "area_perc_":0.0,
    "area_perc":"0.0%"
  },
  "MediumRisk":{
    "cntGFC":0,
    "area_sqm":0.0,
    "hectare":0.0,
    "Thai_rai":0.0,
    "area_perc_":0.0,
    "area_perc":"0.0%"
  },
  "Compliant!":{
    "cntGFC":-1,
    "area_sqm":2414.2719402814,
    "hectare":0.241427194,
    "Thai_rai":1.5089199627,
    "area_perc_":100.0,
    "area_perc":"100.0%"
  }
}